setuptools_cpp/__init__.py
setuptools_cpp/cmake_extension.py
setuptools_cpp/extension_builder.py
setuptools_cpp/py.typed
setuptools_cpp/pybind11_extension.py
setuptools_cpp-0.1.0.dist-info/LICENSE
setuptools_cpp-0.1.0.dist-info/WHEEL
setuptools_cpp-0.1.0.dist-info/METADATA
setuptools_cpp-0.1.0.dist-info/RECORD
