Metadata-Version: 2.1
Name: setuptools-cpp
Version: 0.1.0
Summary: Simplified packaging for pybind11-based C++ extensions
Home-page: https://setuptools-cpp.davidmontague.xyz
License: MIT
Keywords: c++,cpp,extension,pybind11,setup,setuptools
Author: David Montague
Author-email: davwmont@gmail.com
Requires-Python: >=3.6,<4.0
Classifier: Development Status :: 3 - Alpha
Classifier: Intended Audience :: Developers
Classifier: License :: OSI Approved :: MIT License
Classifier: Operating System :: MacOS :: MacOS X
Classifier: Operating System :: Microsoft :: Windows
Classifier: Operating System :: POSIX
Classifier: Programming Language :: Python :: 3
Classifier: Programming Language :: Python :: 3 :: Only
Classifier: Programming Language :: Python :: 3.6
Classifier: Programming Language :: Python :: 3.7
Classifier: Programming Language :: Python :: 3.8
Classifier: Topic :: Software Development
Classifier: Topic :: Utilities
Classifier: Typing :: Typed
Requires-Dist: pybind11
Requires-Dist: setuptools
Project-URL: Documentation, https://setuptools-cpp.davidmontague.xyz
Project-URL: Repository, https://github.com/dmontagu/setuptools-cpp
